xdirsan/__init__.py
xdirsan/main.py
xdirsan/wordlist/wordlist.txt
0xdirsan-0.1.0.dist-info/LICENSE
0xdirsan-0.1.0.dist-info/METADATA
0xdirsan-0.1.0.dist-info/WHEEL
0xdirsan-0.1.0.dist-info/entry_points.txt
0xdirsan-0.1.0.dist-info/top_level.txt
0xdirsan-0.1.0.dist-info/RECORD
