Metadata-Version: 2.1
Name: 0xdirsan
Version: 0.1.0
Summary: 0xdirsan is a simple program designed to search for directories within the file system using brute-force with a given list of words.
Author: x-projetion
Author-email: lutfifakee@proton.me
Classifier: Programming Language :: Python :: 3
Classifier: License :: OSI Approved :: MIT License
Classifier: Operating System :: OS Independent
Requires-Python: >=3.6
License-File: LICENSE
Requires-Dist: requests
Requires-Dist: colorama
